neroBmi/bmi.py
neroBmi-0.0.0.2.dist-info/METADATA
neroBmi-0.0.0.2.dist-info/WHEEL
neroBmi-0.0.0.2.dist-info/top_level.txt
neroBmi-0.0.0.2.dist-info/RECORD
