Metadata-Version: 2.1
Name: neroBmi
Version: 0.0.0.2
Summary: My First Test Package
Home-page: https://blog.naver.com/kirisakirai
Author: Sim
Author-email: dlsnditk119@naver.com
License: MIT
Platform: UNKNOWN
Requires-Python: >=3
